facet/__init__.py
facet/asyncio.py
facet/blocking.py
facet-0.10.1.dist-info/METADATA
facet-0.10.1.dist-info/WHEEL
facet-0.10.1.dist-info/top_level.txt
facet-0.10.1.dist-info/RECORD
