Metadata-Version: 2.1
Name: facet
Version: 0.10.1
Summary: service manager for asyncio
Author: bizywizy
Author-email: pohmelie <multisosnooley@gmail.com>
License: MIT License
Project-URL: Github, https://github.com/pohmelie/facet
Project-URL: Documentation, https://github.com/pohmelie/facet
Classifier: Programming Language :: Python
Classifier: Programming Language :: Python :: 3
Classifier: Development Status :: 5 - Production/Stable
Requires-Python: >=3.11
Provides-Extra: dev
Requires-Dist: pytest-asyncio ; extra == 'dev'
Requires-Dist: pytest-cov ; extra == 'dev'
Requires-Dist: pytest ; extra == 'dev'
Requires-Dist: pre-commit ; extra == 'dev'
Requires-Dist: black ; extra == 'dev'
Requires-Dist: ruff ; extra == 'dev'
Requires-Dist: mypy ; extra == 'dev'
